django_utility_suite/__init__.py
django_utility_suite/api/__init__.py
django_utility_suite/api/mixins/__init__.py
django_utility_suite/api/mixins/cache/__init__.py
django_utility_suite/api/mixins/cache/read_only_viewset_mixin.py
django_utility_suite/api/mixins/utils.py
django_utility_suite/models/__init__.py
django_utility_suite/models/time_stamped.py
django_utility_suite-0.1.11.dist-info/METADATA
django_utility_suite-0.1.11.dist-info/WHEEL
django_utility_suite-0.1.11.dist-info/licenses/LICENSE
django_utility_suite-0.1.11.dist-info/RECORD
