Metadata-Version: 2.4
Name: django_utility_suite
Version: 0.1.11
Summary: A Django utility suite with additional features
License: MIT
License-File: LICENSE
Author: toni
Author-email: tonicapagarcia@gmail.com
Requires-Python: >=3.11,<4.0
Classifier: License :: OSI Approved :: MIT License
Classifier: Programming Language :: Python :: 3
Classifier: Programming Language :: Python :: 3.11
Classifier: Programming Language :: Python :: 3.12
Classifier: Programming Language :: Python :: 3.13
Classifier: Programming Language :: Python :: 3.14
Requires-Dist: django (>=3.0)
Requires-Dist: djangorestframework (>=3.11)
Requires-Dist: xxhash (>=3.5.0,<4.0.0)
